{
  "date": "2026-06-06",
  "generatedAt": "2026-06-06T13:24:33.811Z",
  "minUpvotes": 20,
  "scoredCount": 30,
  "deep": [
    {
      "arxiv_id": "2606.02800",
      "title": "Cosmos 3: Omnimodal World Models for Physical AI",
      "final_score": 7.45,
      "category": "multimodal",
      "autosci_relevance": "indirect",
      "scores": {
        "idea_novelty": 9,
        "system_design_value": 9,
        "transferability_to_autosci": 7,
        "breadth_value": 8,
        "ai_engineering_value": 8,
        "buildability": 4,
        "evaluation_value": 5,
        "evidence_quality": 3
      },
      "one_line": "统一语言、图像、视频、音频和动作的多模态世界模型，为Physical AI提供框架"
    },
    {
      "arxiv_id": "2606.02373",
      "title": "Harness-1: Reinforcement Learning for Search Agents with State-Externalizing Harnesses",
      "final_score": 7.35,
      "category": "agent",
      "autosci_relevance": "direct",
      "scores": {
        "idea_novelty": 8,
        "system_design_value": 9,
        "transferability_to_autosci": 8,
        "breadth_value": 6,
        "ai_engineering_value": 8,
        "buildability": 6,
        "evaluation_value": 5,
        "evidence_quality": 4
      },
      "one_line": "将搜索agent的状态管理外化到环境，用强化学习专注语义决策，提升训练效率。"
    },
    {
      "arxiv_id": "2606.05259",
      "title": "VideoKR: Towards Knowledge- and Reasoning-Intensive Video Understanding",
      "final_score": 7.2,
      "category": "data",
      "autosci_relevance": "direct",
      "scores": {
        "idea_novelty": 6,
        "system_design_value": 8,
        "transferability_to_autosci": 8,
        "breadth_value": 7,
        "ai_engineering_value": 6,
        "buildability": 8,
        "evaluation_value": 8,
        "evidence_quality": 7
      },
      "one_line": "人机协同技能导向数据生成流程，可迁移至自进化数据管线"
    }
  ],
  "radar": [
    {
      "arxiv_id": "2605.31584",
      "title": "LongTraceRL: Learning Long-Context Reasoning from Search Agent Trajectories with Rubric Rewards",
      "final_score": 7,
      "category": "agent",
      "one_line": "利用搜索轨迹和rubric奖励训练长上下文推理"
    },
    {
      "arxiv_id": "2606.02437",
      "title": "On the Scaling of PEFT: Towards Million Personal Models of Trillion Parameters",
      "final_score": 6.95,
      "category": "training",
      "one_line": "探讨将PEFT作为持久化本地状态以实现大规模个性化模型，提供可迁移的缩放模式"
    },
    {
      "arxiv_id": "2606.00408",
      "title": "Masking Stale Observations Helps Search Agents -- Until It Doesn't: A Regime Map and Its Mechanism",
      "final_score": 6.9,
      "category": "agent",
      "one_line": "揭示搜索agent中掩盖陈旧观测的收益与代价及其机制区间"
    },
    {
      "arxiv_id": "2606.06492",
      "title": "Code2LoRA: Hypernetwork-Generated Adapters for Code Language Models under Software Evolution",
      "final_score": 6.9,
      "category": "systems",
      "one_line": "提出Code2LoRA，用超网络生成仓库专用LoRA适配器"
    },
    {
      "arxiv_id": "2606.04743",
      "title": "TIDE: Proactive Multi-Problem Discovery via Template-Guided Iteration",
      "final_score": 6.85,
      "category": "agent",
      "one_line": "模板引导迭代的主动多问题发现框架，可迁移至自主探索系统。"
    },
    {
      "arxiv_id": "2605.29307",
      "title": "GrepSeek: Training Search Agents for Direct Corpus Interaction",
      "final_score": 6.75,
      "category": "agent",
      "one_line": "训练搜索agent通过shell命令直接与语料库交互，提供新型搜索交互模式"
    },
    {
      "arxiv_id": "2605.31268",
      "title": "Mellum2 Technical Report",
      "final_score": 6.75,
      "category": "training",
      "one_line": "12B MoE代码模型的技术报告，展示高效训练和工程模式，可迁移至agent系统构建。"
    },
    {
      "arxiv_id": "2606.05121",
      "title": "Audio Interaction Model",
      "final_score": 6.6,
      "category": "multimodal",
      "one_line": "提出统一的在线音频交互模型，实现实时感知-决策-响应循环"
    },
    {
      "arxiv_id": "2605.30409",
      "title": "SANA-Streaming: Real-time Streaming Video Editing with Hybrid Diffusion Transformer",
      "final_score": 6.35,
      "category": "systems",
      "one_line": "系统算法协同设计实现实时流视频编辑，展示混合架构与推理优化模式"
    },
    {
      "arxiv_id": "2605.31604",
      "title": "Representation Forcing for Bottleneck-Free Unified Multimodal Models",
      "final_score": 6.3,
      "category": "multimodal",
      "one_line": "通过表示预测消除统一多模态模型中的VAE瓶颈，可迁移至多模态接口设计。"
    }
  ]
}
