{
  "date": "2026-05-19",
  "generatedAt": "2026-05-19T19:33:28.964Z",
  "inputFile": "data\\papers\\triage-2026-05-19.json",
  "reviewed": [
    {
      "id": "arxiv-2504-19413",
      "title": "Mem0: Building Production-Ready AI Agents with Scalable Long-Term Memory",
      "file": "data\\papers\\reviewed\\arxiv-2504-19413-2026-05-19.json"
    },
    {
      "id": "arxiv-2605-18747",
      "title": "Code as Agent Harness",
      "file": "data\\papers\\reviewed\\arxiv-2605-18747-2026-05-19.json"
    }
  ],
  "skipped": []
}
